pydeck_carto/__init__.py
pydeck_carto/_version.py
pydeck_carto/layer.py
pydeck_carto/sources.py
pydeck_carto/styles.py
pydeck_carto-0.2.0.dist-info/LICENSE
pydeck_carto-0.2.0.dist-info/METADATA
pydeck_carto-0.2.0.dist-info/WHEEL
pydeck_carto-0.2.0.dist-info/top_level.txt
pydeck_carto-0.2.0.dist-info/RECORD
