Metadata-Version: 2.1
Name: pydeck-carto
Version: 0.2.0
Summary: Pydeck wrapper for use with CARTO
Home-page: https://github.com/visgl/deck.gl/tree/master/bindings/pydeck-carto
Author: CARTO
Author-email: jarroyo@carto.com
License: BSD 3-Clause
Keywords: pydeck,carto,visualization,graphics,GIS,maps
Classifier: Development Status :: 5 - Production/Stable
Classifier: Framework :: Jupyter
Classifier: Intended Audience :: Developers
Classifier: Intended Audience :: Science/Research
Classifier: License :: OSI Approved :: BSD License
Classifier: Natural Language :: English
Classifier: Programming Language :: Python :: 3
Classifier: Programming Language :: Python :: 3.8
Classifier: Programming Language :: Python :: 3.9
Classifier: Programming Language :: Python :: 3.10
Classifier: Programming Language :: Python :: 3.11
Classifier: Programming Language :: Python :: 3.12
Classifier: Programming Language :: Python :: 3.13
Requires-Python: >=3.8
License-File: LICENSE
Requires-Dist: pydeck (>=0.9.0)
Requires-Dist: carto-auth (>=0.2.0)
Requires-Dist: typing-extensions (>=4.0.0)
